{
    "version": "17.66.0.0",
    "description": "QQ音乐去广告精简版",
    "homepage": "https://www.423down.com/193.html",
    "depends": "sudo",
    "extract_dir": "QQMusic",
    "url": "http://xqh.ma:33001/ltrump-onedrive/raresoftware/QQMusic_v17.66.0.0.7z",
    "hash": "a37784fe09e075a46305ca9774f5ce4d1cc7af679292c0b7fc69e7b2fb7e7b92",
    "installer": {
        "script": "sudo cmd /c \"$dir\\!绿化.bat\""
    },
    "uninstaller": {
        "script": "sudo cmd /c \"$dir\\!卸载.bat\""
    },
    "shortcuts": [
        [
            "QQMusic.exe",
            "..\\腾讯软件\\QQ音乐"
        ]
    ],
    "bin": [
        [
            "QQMusic.exe",
            "qqmusic"
        ]
    ],
    "checkver": {
        "encode": "UTF-8",
        "re": "v([\\d.]+)"
    },
    "autoupdate": {
        "url": "http://xqh.ma:33001/ltrump-onedrive/raresoftware/QQMusic_v$version.7z"
    }
}
